dataref/__init__.py
dataref/cons/constants.py
dataref/pipeline/__init__.py
dataref/pipeline/financial_nse_pipeline.py
dataref/pipeline/shareholding_nse_pipeline.py
dataref/util/__init__.py
dataref/util/download_nse_financial_result_xbrl.py
dataref/util/download_nse_shareholding_xbrl.py
dataref-0.1.0.dist-info/licenses/LICENSE
dataref-0.1.0.dist-info/METADATA
dataref-0.1.0.dist-info/WHEEL
dataref-0.1.0.dist-info/top_level.txt
dataref-0.1.0.dist-info/RECORD
