Metadata-Version: 2.4
Name: dataref
Version: 0.1.0
Summary: A package for processing NSE financial and shareholding XBRL data
Home-page: https://github.com/shanand-madihum/dataref
Author: Sudhir Reddy
License-Expression: MIT
Project-URL: Homepage, https://github.com/shanand-madihum/dataref
Project-URL: Repository, https://github.com/shanand-madihum/dataref
Requires-Python: >=3.8
License-File: LICENSE
Requires-Dist: pandas>=2.0.0
Requires-Dist: requests>=2.28.0
Requires-Dist: beautifulsoup4>=4.11.0
Requires-Dist: lxml>=4.9.0
Requires-Dist: numpy>=1.24.0
Requires-Dist: python-dateutil>=2.8.2
Dynamic: home-page
Dynamic: license-file
Dynamic: requires-python
